{
"type": "FeatureCollection",
"name": "bostonloganairport_point4326",
"crs": { "type": "name", "properties": { "name": "urn:ogc:def:crs:OGC:1.3:CRS84" } },
"features": [
{ "type": "Feature", "properties": { "Name": "Boston Logan Airport" }, "geometry": { "type": "Point", "coordinates": [ -71.019346845799049, 42.366156365547454 ] } }
]
}
